pyo3_stubgen/__init__.py
pyo3_stubgen/generate.py
pyo3_stubgen-0.3.0.dist-info/LICENSE
pyo3_stubgen-0.3.0.dist-info/METADATA
pyo3_stubgen-0.3.0.dist-info/WHEEL
pyo3_stubgen-0.3.0.dist-info/entry_points.txt
pyo3_stubgen-0.3.0.dist-info/top_level.txt
pyo3_stubgen-0.3.0.dist-info/RECORD
