Metadata-Version: 2.1
Name: pyo3-stubgen
Version: 0.3.0
Summary: Enable hinting for pyo3 extension modules by generating type and docstring stubs
Author: Mike Foster
License: MIT
Project-URL: Documentation, https://musicalninjas.github.io/pyo3-stubgen
Project-URL: Repository, https://github.com/MusicalNinjas/pyo3-stubgen
Project-URL: Issues, https://github.com/MusicalNinjas/pyo3-stubgen/issues
Project-URL: Changelog, https://github.com/MusicalNinjas/pyo3-stubgen/blob/main/CHANGELOG.md
Classifier: Programming Language :: Python :: 3
Classifier: Programming Language :: Rust
Classifier: License :: OSI Approved :: MIT License
Classifier: Operating System :: OS Independent
Classifier: Topic :: Software Development :: Libraries :: Python Modules
Classifier: Intended Audience :: Developers
Classifier: Natural Language :: English
Requires-Python: >=3.8
License-File: LICENSE
Requires-Dist: click
Provides-Extra: cov
Requires-Dist: pyo3-stubgen[test] ; extra == 'cov'
Requires-Dist: pytest-cov ; extra == 'cov'
Provides-Extra: dev
Requires-Dist: pyo3-stubgen[cov,doc,lint,test] ; extra == 'dev'
Provides-Extra: doc
Requires-Dist: black ; extra == 'doc'
Requires-Dist: mkdocs ; extra == 'doc'
Requires-Dist: mkdocstrings[python] ; extra == 'doc'
Requires-Dist: mkdocs-material ; extra == 'doc'
Provides-Extra: lint
Requires-Dist: ruff ; extra == 'lint'
Provides-Extra: test
Requires-Dist: pytest ; extra == 'test'
Requires-Dist: pytest-doctest-mkdocstrings ; extra == 'test'
